banana_i18n/__init__.py
banana_i18n/fallback.json
banana_i18n/plural.py
banana_i18n/py.typed
banana_i18n-0.1.3.dist-info/METADATA
banana_i18n-0.1.3.dist-info/WHEEL
banana_i18n-0.1.3.dist-info/top_level.txt
banana_i18n-0.1.3.dist-info/RECORD
