Metadata-Version: 2.1
Name: banana-i18n
Version: 0.1.3
Summary: An i18n library based on the banana message format
Home-page: https://git.legoktm.com/legoktm/banana-i18n
Author: Kunal Mehta
Author-email: legoktm@member.fsf.org
License: MIT
Platform: UNKNOWN
Requires-Python: >=3.5
